ziranpai/__init__.py
ziranpai/ziranpai_main.py
ziranpai-0.1.1.dist-info/METADATA
ziranpai-0.1.1.dist-info/WHEEL
ziranpai-0.1.1.dist-info/entry_points.txt
ziranpai-0.1.1.dist-info/top_level.txt
ziranpai-0.1.1.dist-info/RECORD
