Metadata-Version: 2.4
Name: ziranpai
Version: 0.1.1
Summary: 一个类似自然语言的中文编程语言：自然派。
Author-email: amozeng <1019191262@qq.com>
Classifier: Programming Language :: Python :: 3
Classifier: License :: OSI Approved :: MIT License
Classifier: Operating System :: OS Independent
Requires-Python: >=3.7
